habushu_uv_publish_to_dev_repo/__init__.py
habushu_uv_publish_to_dev_repo/py.typed
habushu_uv_publish_to_dev_repo-3.1.0.dev1750247662.dist-info/METADATA
habushu_uv_publish_to_dev_repo-3.1.0.dev1750247662.dist-info/WHEEL
habushu_uv_publish_to_dev_repo-3.1.0.dev1750247662.dist-info/RECORD
