Metadata-Version: 2.4
Name: habushu-uv-publish-to-dev-repo
Version: 3.1.0.dev1750247662
Summary: Example of how to use Habushu to publish to a development repository
Author-email: Margaret Black <black_margaret@bah.com>
Requires-Python: >=3.12
